MANIFEST.in
README.rst
setup.cfg
setup.py
bbcondeparser/__init__.py
bbcondeparser/_six.py
bbcondeparser/errors.py
bbcondeparser/html_tags.py
bbcondeparser/tags.py
bbcondeparser/token_parser.py
bbcondeparser/tree_parser.py
bbcondeparser/utils.py
bbcondeparser.egg-info/PKG-INFO
bbcondeparser.egg-info/SOURCES.txt
bbcondeparser.egg-info/dependency_links.txt
bbcondeparser.egg-info/top_level.txt