Metadata-Version: 1.1
Name: bbcondeparser
Version: 1.0.0
Summary: parser for Conde Nast BBCode
Home-page: https://github.com/cnduk/bbcondeparser
Author: Conde Nast Digital UK
Author-email: condenet.technical@condenast.co.uk
License: MIT
Download-URL: https://github.com/cnduk/bbcondeparser/tarball/v1.0.0
Keywords: bbcode
Platform: UNKNOWN
Classifier: License :: OSI Approved :: MIT License
Classifier: Intended Audience :: Developers
Classifier: Programming Language :: Python :: 2
Classifier: Programming Language :: Python :: 2.7
Classifier: Programming Language :: Python :: 3.3
Classifier: Programming Language :: Python :: 3.4
Classifier: Programming Language :: Python :: 3.5
Classifier: Programming Language :: Python :: 3.6
Classifier: Topic :: Text Processing :: Markup
